Workbook

Sheet Calculadora
A1: w
C2: CALCULADORA GENESIS COMMUNITY V3 | L2: PLANTILLA TUNEOS
L3: ="Matrícula: " & TEXT(C30, "") -> Matrícula:
C4: MODELO | E4: CATEGORÍA | H4: PRESUPUESTO | L4: ="Modelo: " & TEXT(C6, "") -> Modelo: Ruffian
C5: ruffian | E5: =VLOOKUP(C5,Listado!A:F,4,FALSE) -> Motos | H5: MOTOR | J5: =IF(D11, E7*0.15, 0) + IF(D11, 300, 0) -> 3225 | L5: ="Modificación: " & IF(D7, "Full Tuning", IF(D11, "Motor", "") & IF(D13>0, "+ Performance (" & D13 & " piezas) ", "") & IF(D15>0, "+ Custom (" & D15 & " piezas) ", "") & IF(D17>0, "+ Cosmetic (" & D17 & " piezas) ", "") ) & IF(D9, "+ Pintura camaleónica ", "") & IF(D20, "+ Reparación", "") -> Modificación: Motor
C6: =VLOOKUP(C5,Listado!A:F,2,FALSE) -> Ruffian | E6: <-- NOMBRE IC | H6: PERFORMANCE | J6: =IF(D13>0, E7*0.15, 0) + D13*200 -> 0 | L6: ="Importe: " & TEXT(J9, "#$") -> Importe: 2580$
C7: FULL TUNNING | D7: FALSE | E7: =VLOOKUP(C5,Listado!A:F,3,FALSE) -> 19500 | H7: CUSTOM | J7: =IF(D15>0, E7*0.05, 0) + D15*100 -> 0 | L7: ="Empleado que realizo el servicio: " & TEXT(C27, "") -> Empleado que realizo el servicio:
H8: COSMETIC | J8: =IF(D17>0, E7*0.05, 0) + D17*50 -> 0 | L8: ="Convenio y descuento: " & I16 & " (" & I13 & "%)" -> Convenio y descuento: N/A (20%)
C9: PINTURA CAMALEÓNICA | D9: FALSE | E9: MECÁNICA | H9: PRECIO TOTAL | J9: =IF(E5="VIP", IF(D7, 5000 + IF(D11,300,0) + D13*200 + D15*100 + D17*50 + IF(D20,D24,0), IF(D11,1000,0) + D13*1000 + D15*1000 + D17*1000 + IF(D20,D24,0) ), IF(D7, (E7*0.4)*(1-(I13/100)) + IF(D20,D24,0), ( IF(D11,E7*0.15,0) + IF(D13>0,E7*0.15,0) + IF(D15>0,E7*0.05,0) + IF(D17>0,E7*0.05,0) + IF(D11,300,0) + D13*200 + D15*100 + D17*50 )*(1-(I13/100)) + IF(D20,D24,0) ) )+ IF(D9, 5000, 0) -> 2580
C10: MOTOR | E10: PIEZAS
C11: PIEZAS | D11: TRUE | E11: FULL | F11: FALSE | L11: PLANTILLA REPARACIONES
C12: PERFORMANCE | H12: DESCUENTO (%) | L12: ="Matrícula: " & TEXT(C30, "") -> Matrícula:
C13: PIEZAS | D13: 0 | H13: PORCENTAJE | I13: 20 | L13: ="Modelo: " & TEXT(C6, "") -> Modelo: Ruffian
C14: CUSTOM | L14: ="Modificación: Reparación" -> Modificación: Reparación
C15: PIEZAS | D15: 0 | H15: NEGOCIOS | L15: ="Importe: " & TEXT(D24, "#$") -> Importe: $
C16: COSMETIC | H16: NEGOCIOS | I16: N/A | L16: ="Empleado que realizo el servicio: " & TEXT(C27, "") -> Empleado que realizo el servicio:
C17: PIEZAS | L17: ="Convenio y descuento: " & I16 & " (" & I13 & "%)" -> Convenio y descuento: N/A (20%)
C20: REPARACIÓN | D20: FALSE
C21: Partes del chasis | D21: 0
C22: Partes esenciales | D22: 0 | H22: =IFERROR(_xludf.IMAGE(VLOOKUP(C6,Listado!A:E,5,FALSE)), "No hay imagen para este vehículo") -> No hay imagen para este vehículo
C23: Partes de servicio | D23: 0
C24: PRECIO TOTAL | D24: =((D21*30) + (D22*65) + (D23*40)) * (1 - I13/100) -> 0
C26: NOMBRE DEL MECÁNICO
C29: Matrícula
H37: =IFERROR(_xludf.IMAGE(VLOOKUP(C26,Listado!A:E,5,FALSE)), "No hay imagen para este vehículo") -> No hay imagen para este vehículo
H52: =IFERROR(_xludf.IMAGE(VLOOKUP(C39,Listado!A:E,5,FALSE)), "No hay imagen para este vehículo") -> No hay imagen para este vehículo
H67: =IFERROR(_xludf.IMAGE(VLOOKUP(C54,Listado!A:E,5,FALSE)), "No hay imagen para este vehículo") -> No hay imagen para este vehículo
H82: =IFERROR(_xludf.IMAGE(VLOOKUP(C69,Listado!A:E,5,FALSE)), "No hay imagen para este vehículo") -> No hay imagen para este vehículo
H97: =IFERROR(_xludf.IMAGE(VLOOKUP(C84,Listado!A:E,5,FALSE)), "No hay imagen para este vehículo") -> No hay imagen para este vehículo
H112: =IFERROR(_xludf.IMAGE(VLOOKUP(C99,Listado!A:E,5,FALSE)), "No hay imagen para este vehículo") -> No hay imagen para este vehículo
H127: =IFERROR(_xludf.IMAGE(VLOOKUP(C114,Listado!A:E,5,FALSE)), "No hay imagen para este vehículo") -> No hay imagen para este vehículo
H142: =IFERROR(_xludf.IMAGE(VLOOKUP(C129,Listado!A:E,5,FALSE)), "No hay imagen para este vehículo") -> No hay imagen para este vehículo
H157: =IFERROR(_xludf.IMAGE(VLOOKUP(C144,Listado!A:E,5,FALSE)), "No hay imagen para este vehículo") -> No hay imagen para este vehículo
H172: =IFERROR(_xludf.IMAGE(VLOOKUP(C159,Listado!A:E,5,FALSE)), "No hay imagen para este vehículo") -> No hay imagen para este vehículo
H187: =IFERROR(_xludf.IMAGE(VLOOKUP(C174,Listado!A:E,5,FALSE)), "No hay imagen para este vehículo") -> No hay imagen para este vehículo
H202: =IFERROR(_xludf.IMAGE(VLOOKUP(C189,Listado!A:E,5,FALSE)), "No hay imagen para este vehículo") -> No hay imagen para este vehículo
H217: =IFERROR(_xludf.IMAGE(VLOOKUP(C204,Listado!A:E,5,FALSE)), "No hay imagen para este vehículo") -> No hay imagen para este vehículo

Sheet Listado
A1: Modelo | B1: Nombre | C1: Precio | D1: Categoría | E1: FOTOS
A2: =IFERROR(__xludf.DUMMYFUNCTION("IMPORTRANGE(""https://docs.google.com/spreadsheets/d/1mjNNDGrvmUts6VjAqwo43L28lC7JMK2L6g8bGEhk9BI/edit?gid=1084388773#gid=1084388773"", ""A2:E990"")"),"bmx") -> bmx | B2: =IFERROR(__xludf.DUMMYFUNCTION("""COMPUTED_VALUE"""),"BMX") -> BMX | C2: =IFERROR(__xludf.DUMMYFUNCTION("""COMPUTED_VALUE"""),1500) -> 1500 | D2: =IFERROR(__xludf.DUMMYFUNCTION("""COMPUTED_VALUE"""),"Bicicletas") -> Bicicletas | E2: =IFERROR(__xludf.DUMMYFUNCTION("""COMPUTED_VALUE"""),"https://docs.fivem.net/vehicles/bmx.webp") -> https://docs.fivem.net/vehicles/bmx.webp
A3: =IFERROR(__xludf.DUMMYFUNCTION("""COMPUTED_VALUE"""),"cruiser") -> cruiser | B3: =IFERROR(__xludf.DUMMYFUNCTION("""COMPUTED_VALUE"""),"Cruiser") -> Cruiser | C3: =IFERROR(__xludf.DUMMYFUNCTION("""COMPUTED_VALUE"""),1000) -> 1000 | D3: =IFERROR(__xludf.DUMMYFUNCTION("""COMPUTED_VALUE"""),"Bicicletas") -> Bicicletas | E3: =IFERROR(__xludf.DUMMYFUNCTION("""COMPUTED_VALUE"""),"https://docs.fivem.net/vehicles/cruiser.webp") -> https://docs.fivem.net/vehicles/cruiser.webp
A4: =IFERROR(__xludf.DUMMYFUNCTION("""COMPUTED_VALUE"""),"fixter") -> fixter | B4: =IFERROR(__xludf.DUMMYFUNCTION("""COMPUTED_VALUE"""),"Fixter") -> Fixter | C4: =IFERROR(__xludf.DUMMYFUNCTION("""COMPUTED_VALUE"""),1200) -> 1200 | D4: =IFERROR(__xludf.DUMMYFUNCTION("""COMPUTED_VALUE"""),"Bicicletas") -> Bicicletas | E4: =IFERROR(__xludf.DUMMYFUNCTION("""COMPUTED_VALUE"""),"https://docs.fivem.net/vehicles/fixter.webp") -> https://docs.fivem.net/vehicles/fixter.webp
A5: =IFERROR(__xludf.DUMMYFUNCTION("""COMPUTED_VALUE"""),"inductor") -> inductor | B5: =IFERROR(__xludf.DUMMYFUNCTION("""COMPUTED_VALUE"""),"Inductor") -> Inductor | C5: =IFERROR(__xludf.DUMMYFUNCTION("""COMPUTED_VALUE"""),7500) -> 7500 | D5: =IFERROR(__xludf.DUMMYFUNCTION("""COMPUTED_VALUE"""),"Bicicletas") -> Bicicletas | E5: =IFERROR(__xludf.DUMMYFUNCTION("""COMPUTED_VALUE"""),"https://docs.fivem.net/vehicles/inductor.webp") -> https://docs.fivem.net/vehicles/inductor.webp
A6: =IFERROR(__xludf.DUMMYFUNCTION("""COMPUTED_VALUE"""),"inductor2") -> inductor2 | B6: =IFERROR(__xludf.DUMMYFUNCTION("""COMPUTED_VALUE"""),"Junk Energy Inductor") -> Junk Energy Inductor | C6: =IFERROR(__xludf.DUMMYFUNCTION("""COMPUTED_VALUE"""),8200) -> 8200 | D6: =IFERROR(__xludf.DUMMYFUNCTION("""COMPUTED_VALUE"""),"Bicicletas") -> Bicicletas | E6: =IFERROR(__xludf.DUMMYFUNCTION("""COMPUTED_VALUE"""),"https://docs.fivem.net/vehicles/inductor2.webp") -> https://docs.fivem.net/vehicles/inductor2.webp
A7: =IFERROR(__xludf.DUMMYFUNCTION("""COMPUTED_VALUE"""),"scorcher") -> scorcher | B7: =IFERROR(__xludf.DUMMYFUNCTION("""COMPUTED_VALUE"""),"Scorcher") -> Scorcher | C7: =IFERROR(__xludf.DUMMYFUNCTION("""COMPUTED_VALUE"""),2000) -> 2000 | D7: =IFERROR(__xludf.DUMMYFUNCTION("""COMPUTED_VALUE"""),"Bicicletas") -> Bicicletas | E7: =IFERROR(__xludf.DUMMYFUNCTION("""COMPUTED_VALUE"""),"https://docs.fivem.net/vehicles/scorcher.webp") -> https://docs.fivem.net/vehicles/scorcher.webp
A8: =IFERROR(__xludf.DUMMYFUNCTION("""COMPUTED_VALUE"""),"tribike") -> tribike | B8: =IFERROR(__xludf.DUMMYFUNCTION("""COMPUTED_VALUE"""),"Whippet Race Bike") -> Whippet Race Bike | C8: =IFERROR(__xludf.DUMMYFUNCTION("""COMPUTED_VALUE"""),1700) -> 1700 | D8: =IFERROR(__xludf.DUMMYFUNCTION("""COMPUTED_VALUE"""),"Bicicletas") -> Bicicletas | E8: =IFERROR(__xludf.DUMMYFUNCTION("""COMPUTED_VALUE"""),"https://docs.fivem.net/vehicles/tribike.webp") -> https://docs.fivem.net/vehicles/tribike.webp
A9: =IFERROR(__xludf.DUMMYFUNCTION("""COMPUTED_VALUE"""),"tribike2") -> tribike2 | B9: =IFERROR(__xludf.DUMMYFUNCTION("""COMPUTED_VALUE"""),"Endurex Race Bike") -> Endurex Race Bike | C9: =IFERROR(__xludf.DUMMYFUNCTION("""COMPUTED_VALUE"""),1700) -> 1700 | D9: =IFERROR(__xludf.DUMMYFUNCTION("""COMPUTED_VALUE"""),"Bicicletas") -> Bicicletas | E9: =IFERROR(__xludf.DUMMYFUNCTION("""COMPUTED_VALUE"""),"https://docs.fivem.net/vehicles/tribike2.webp") -> https://docs.fivem.net/vehicles/tribike2.webp
A10: =IFERROR(__xludf.DUMMYFUNCTION("""COMPUTED_VALUE"""),"tribike3") -> tribike3 | B10: =IFERROR(__xludf.DUMMYFUNCTION("""COMPUTED_VALUE"""),"Tri-cycle Race Bike") -> Tri-cycle Race Bike | C10: =IFERROR(__xludf.DUMMYFUNCTION("""COMPUTED_VALUE"""),1800) -> 1800 | D10: =IFERROR(__xludf.DUMMYFUNCTION("""COMPUTED_VALUE"""),"Bicicletas") -> Bicicletas | E10: =IFERROR(__xludf.DUMMYFUNCTION("""COMPUTED_VALUE"""),"https://docs.fivem.net/vehicles/tribike3.webp") -> https://docs.fivem.net/vehicles/tribike3.webp
A11: =IFERROR(__xludf.DUMMYFUNCTION("""COMPUTED_VALUE"""),"formula") -> formula | B11: =IFERROR(__xludf.DUMMYFUNCTION("""COMPUTED_VALUE"""),"PR4") -> PR4 | C11: =IFERROR(__xludf.DUMMYFUNCTION("""COMPUTED_VALUE"""),1000000) -> 1000000 | D11: =IFERROR(__xludf.DUMMYFUNCTION("""COMPUTED_VALUE"""),"Circuitos") -> Circuitos | E11: =IFERROR(__xludf.DUMMYFUNCTION("""COMPUTED_VALUE"""),"https://docs.fivem.net/vehicles/formula.webp") -> https://docs.fivem.net/vehicles/formula.webp
A12: =IFERROR(__xludf.DUMMYFUNCTION("""COMPUTED_VALUE"""),"formula2") -> formula2 | B12: =IFERROR(__xludf.DUMMYFUNCTION("""COMPUTED_VALUE"""),"R88") -> R88 | C12: =IFERROR(__xludf.DUMMYFUNCTION("""COMPUTED_VALUE"""),1000000) -> 1000000 | D12: =IFERROR(__xludf.DUMMYFUNCTION("""COMPUTED_VALUE"""),"Circuitos") -> Circuitos | E12: =IFERROR(__xludf.DUMMYFUNCTION("""COMPUTED_VALUE"""),"https://docs.fivem.net/vehicles/formula2.webp") -> https://docs.fivem.net/vehicles/formula2.webp
A13: =IFERROR(__xludf.DUMMYFUNCTION("""COMPUTED_VALUE"""),"openwheel1") -> openwheel1 | B13: =IFERROR(__xludf.DUMMYFUNCTION("""COMPUTED_VALUE"""),"BR8") -> BR8 | C13: =IFERROR(__xludf.DUMMYFUNCTION("""COMPUTED_VALUE"""),2000000) -> 2000000 | D13: =IFERROR(__xludf.DUMMYFUNCTION("""COMPUTED_VALUE"""),"Circuitos") -> Circuitos | E13: =IFERROR(__xludf.DUMMYFUNCTION("""COMPUTED_VALUE"""),"https://docs.fivem.net/vehicles/openwheel1.webp") -> https://docs.fivem.net/vehicles/openwheel1.webp
A14: =IFERROR(__xludf.DUMMYFUNCTION("""COMPUTED_VALUE"""),"openwheel2") -> openwheel2 | B14: =IFERROR(__xludf.DUMMYFUNCTION("""COMPUTED_VALUE"""),"DR1") -> DR1 | C14: =IFERROR(__xludf.DUMMYFUNCTION("""COMPUTED_VALUE"""),1500000) -> 1500000 | D14: =IFERROR(__xludf.DUMMYFUNCTION("""COMPUTED_VALUE"""),"Circuitos") -> Circuitos | E14: =IFERROR(__xludf.DUMMYFUNCTION("""COMPUTED_VALUE"""),"https://docs.fivem.net/vehicles/openwheel2.webp") -> https://docs.fivem.net/vehicles/openwheel2.webp
A15: =IFERROR(__xludf.DUMMYFUNCTION("""COMPUTED_VALUE"""),"asbo") -> asbo | B15: =IFERROR(__xludf.DUMMYFUNCTION("""COMPUTED_VALUE"""),"Asbo") -> Asbo | C15: =IFERROR(__xludf.DUMMYFUNCTION("""COMPUTED_VALUE"""),2500) -> 2500 | D15: =IFERROR(__xludf.DUMMYFUNCTION("""COMPUTED_VALUE"""),"Compactos") -> Compactos | E15: =IFERROR(__xludf.DUMMYFUNCTION("""COMPUTED_VALUE"""),"https://docs.fivem.net/vehicles/asbo.webp") -> https://docs.fivem.net/vehicles/asbo.webp
A16: =IFERROR(__xludf.DUMMYFUNCTION("""COMPUTED_VALUE"""),"blista") -> blista | B16: =IFERROR(__xludf.DUMMYFUNCTION("""COMPUTED_VALUE"""),"Blista") -> Blista | C16: =IFERROR(__xludf.DUMMYFUNCTION("""COMPUTED_VALUE"""),4000) -> 4000 | D16: =IFERROR(__xludf.DUMMYFUNCTION("""COMPUTED_VALUE"""),"Compactos") -> Compactos | E16: =IFERROR(__xludf.DUMMYFUNCTION("""COMPUTED_VALUE"""),"https://docs.fivem.net/vehicles/blista.webp") -> https://docs.fivem.net/vehicles/blista.webp
A17: =IFERROR(__xludf.DUMMYFUNCTION("""COMPUTED_VALUE"""),"blista2") -> blista2 | B17: =IFERROR(__xludf.DUMMYFUNCTION("""COMPUTED_VALUE"""),"Blista Compact") -> Blista Compact | C17: =IFERROR(__xludf.DUMMYFUNCTION("""COMPUTED_VALUE"""),15000) -> 15000 | D17: =IFERROR(__xludf.DUMMYFUNCTION("""COMPUTED_VALUE"""),"Compactos") -> Compactos | E17: =IFERROR(__xludf.DUMMYFUNCTION("""COMPUTED_VALUE"""),"https://docs.fivem.net/vehicles/blista2.webp") -> https://docs.fivem.net/vehicles/blista2.webp
A18: =IFERROR(__xludf.DUMMYFUNCTION("""COMPUTED_VALUE"""),"blista3") -> blista3 | B18: =IFERROR(__xludf.DUMMYFUNCTION("""COMPUTED_VALUE"""),"Blista Go Go Monkey") -> Blista Go Go Monkey | C18: =IFERROR(__xludf.DUMMYFUNCTION("""COMPUTED_VALUE"""),15000) -> 15000 | D18: =IFERROR(__xludf.DUMMYFUNCTION("""COMPUTED_VALUE"""),"Compactos") -> Compactos | E18: =IFERROR(__xludf.DUMMYFUNCTION("""COMPUTED_VALUE"""),"https://docs.fivem.net/vehicles/blista3.webp") -> https://docs.fivem.net/vehicles/blista3.webp
A19: =IFERROR(__xludf.DUMMYFUNCTION("""COMPUTED_VALUE"""),"boor") -> boor | B19: =IFERROR(__xludf.DUMMYFUNCTION("""COMPUTED_VALUE"""),"Boor") -> Boor | C19: =IFERROR(__xludf.DUMMYFUNCTION("""COMPUTED_VALUE"""),13500) -> 13500 | D19: =IFERROR(__xludf.DUMMYFUNCTION("""COMPUTED_VALUE"""),"Compactos") -> Compactos | E19: =IFERROR(__xludf.DUMMYFUNCTION("""COMPUTED_VALUE"""),"https://docs.fivem.net/vehicles/boor.webp") -> https://docs.fivem.net/vehicles/boor.webp
A20: =IFERROR(__xludf.DUMMYFUNCTION("""COMPUTED_VALUE"""),"brioso") -> brioso | B20: =IFERROR(__xludf.DUMMYFUNCTION("""COMPUTED_VALUE"""),"Brioso R/A") -> Brioso R/A | C20: =IFERROR(__xludf.DUMMYFUNCTION("""COMPUTED_VALUE"""),13500) -> 13500 | D20: =IFERROR(__xludf.DUMMYFUNCTION("""COMPUTED_VALUE"""),"Compactos") -> Compactos | E20: =IFERROR(__xludf.DUMMYFUNCTION("""COMPUTED_VALUE"""),"https://docs.fivem.net/vehicles/lectro.webp") -> https://docs.fivem.net/vehicles/lectro.webp
A21: =IFERROR(__xludf.DUMMYFUNCTION("""COMPUTED_VALUE"""),"brioso2") -> brioso2 | B21: =IFERROR(__xludf.DUMMYFUNCTION("""COMPUTED_VALUE"""),"Brioso 300") -> Brioso 300 | C21: =IFERROR(__xludf.DUMMYFUNCTION("""COMPUTED_VALUE"""),4500) -> 4500 | D21: =IFERROR(__xludf.DUMMYFUNCTION("""COMPUTED_VALUE"""),"Compactos") -> Compactos | E21: =IFERROR(__xludf.DUMMYFUNCTION("""COMPUTED_VALUE"""),"https://docs.fivem.net/vehicles/brioso2.webp") -> https://docs.fivem.net/vehicles/brioso2.webp
A22: =IFERROR(__xludf.DUMMYFUNCTION("""COMPUTED_VALUE"""),"club") -> club | B22: =IFERROR(__xludf.DUMMYFUNCTION("""COMPUTED_VALUE"""),"Club") -> Club | C22: =IFERROR(__xludf.DUMMYFUNCTION("""COMPUTED_VALUE"""),12500) -> 12500 | D22: =IFERROR(__xludf.DUMMYFUNCTION("""COMPUTED_VALUE"""),"Compactos") -> Compactos | E22: =IFERROR(__xludf.DUMMYFUNCTION("""COMPUTED_VALUE"""),"https://docs.fivem.net/vehicles/club.webp") -> https://docs.fivem.net/vehicles/club.webp
A23: =IFERROR(__xludf.DUMMYFUNCTION("""COMPUTED_VALUE"""),"dilettante") -> dilettante | B23: =IFERROR(__xludf.DUMMYFUNCTION("""COMPUTED_VALUE"""),"Dilettante") -> Dilettante | C23: =IFERROR(__xludf.DUMMYFUNCTION("""COMPUTED_VALUE"""),9000) -> 9000 | D23: =IFERROR(__xludf.DUMMYFUNCTION("""COMPUTED_VALUE"""),"Compactos") -> Compactos | E23: =IFERROR(__xludf.DUMMYFUNCTION("""COMPUTED_VALUE"""),"https://docs.fivem.net/vehicles/dilettante.webp") -> https://docs.fivem.net/vehicles/dilettante.webp
A24: =IFERROR(__xludf.DUMMYFUNCTION("""COMPUTED_VALUE"""),"issi2") -> issi2 | B24: =IFERROR(__xludf.DUMMYFUNCTION("""COMPUTED_VALUE"""),"Issi") -> Issi | C24: =IFERROR(__xludf.DUMMYFUNCTION("""COMPUTED_VALUE"""),7000) -> 7000 | D24: =IFERROR(__xludf.DUMMYFUNCTION("""COMPUTED_VALUE"""),"Compactos") -> Compactos | E24: =IFERROR(__xludf.DUMMYFUNCTION("""COMPUTED_VALUE"""),"https://docs.fivem.net/vehicles/issi2.webp") -> https://docs.fivem.net/vehicles/issi2.webp
A25: =IFERROR(__xludf.DUMMYFUNCTION("""COMPUTED_VALUE"""),"issi3") -> issi3 | B25: =IFERROR(__xludf.DUMMYFUNCTION("""COMPUTED_VALUE"""),"Issi Classic") -> Issi Classic | C25: =IFERROR(__xludf.DUMMYFUNCTION("""COMPUTED_VALUE"""),3900) -> 3900 | D25: =IFERROR(__xludf.DUMMYFUNCTION("""COMPUTED_VALUE"""),"Compactos") -> Compactos | E25: =IFERROR(__xludf.DUMMYFUNCTION("""COMPUTED_VALUE"""),"https://docs.fivem.net/vehicles/issi3.webp") -> https://docs.fivem.net/vehicles/issi3.webp
A26: =IFERROR(__xludf.DUMMYFUNCTION("""COMPUTED_VALUE"""),"issi4") -> issi4 | B26: =IFERROR(__xludf.DUMMYFUNCTION("""COMPUTED_VALUE"""),"Issi Arena") -> Issi Arena | C26: =IFERROR(__xludf.DUMMYFUNCTION("""COMPUTED_VALUE"""),61000) -> 61000 | D26: =IFERROR(__xludf.DUMMYFUNCTION("""COMPUTED_VALUE"""),"Compactos") -> Compactos | E26: =IFERROR(__xludf.DUMMYFUNCTION("""COMPUTED_VALUE"""),"https://docs.fivem.net/vehicles/issi4.webp") -> https://docs.fivem.net/vehicles/issi4.webp
A27: =IFERROR(__xludf.DUMMYFUNCTION("""COMPUTED_VALUE"""),"issi5") -> issi5 | B27: =IFERROR(__xludf.DUMMYFUNCTION("""COMPUTED_VALUE"""),"Issi Future Shock") -> Issi Future Shock | C27: =IFERROR(__xludf.DUMMYFUNCTION("""COMPUTED_VALUE"""),68500) -> 68500 | D27: =IFERROR(__xludf.DUMMYFUNCTION("""COMPUTED_VALUE"""),"Compactos") -> Compactos | E27: =IFERROR(__xludf.DUMMYFUNCTION("""COMPUTED_VALUE"""),"https://docs.fivem.net/vehicles/issi5.webp") -> https://docs.fivem.net/vehicles/issi5.webp
A28: =IFERROR(__xludf.DUMMYFUNCTION("""COMPUTED_VALUE"""),"issi6") -> issi6 | B28: =IFERROR(__xludf.DUMMYFUNCTION("""COMPUTED_VALUE"""),"Issi Nightmare") -> Issi Nightmare | C28: =IFERROR(__xludf.DUMMYFUNCTION("""COMPUTED_VALUE"""),70000) -> 70000 | D28: =IFERROR(__xludf.DUMMYFUNCTION("""COMPUTED_VALUE"""),"Compactos") -> Compactos | E28: =IFERROR(__xludf.DUMMYFUNCTION("""COMPUTED_VALUE"""),"https://docs.fivem.net/vehicles/issi6.webp") -> https://docs.fivem.net/vehicles/issi6.webp
A29: =IFERROR(__xludf.DUMMYFUNCTION("""COMPUTED_VALUE"""),"issi7") -> issi7 | B29: =IFERROR(__xludf.DUMMYFUNCTION("""COMPUTED_VALUE"""),"Issi Sport") -> Issi Sport | C29: =IFERROR(__xludf.DUMMYFUNCTION("""COMPUTED_VALUE"""),150000) -> 150000 | D29: =IFERROR(__xludf.DUMMYFUNCTION("""COMPUTED_VALUE"""),"Compactos") -> Compactos | E29: =IFERROR(__xludf.DUMMYFUNCTION("""COMPUTED_VALUE"""),"https://docs.fivem.net/vehicles/issi7.webp") -> https://docs.fivem.net/vehicles/issi7.webp
A30: =IFERROR(__xludf.DUMMYFUNCTION("""COMPUTED_VALUE"""),"issi8") -> issi8 | B30: =IFERROR(__xludf.DUMMYFUNCTION("""COMPUTED_VALUE"""),"Issi Rally") -> Issi Rally | C30: =IFERROR(__xludf.DUMMYFUNCTION("""COMPUTED_VALUE"""),140000) -> 140000 | D30: =IFERROR(__xludf.DUMMYFUNCTION("""COMPUTED_VALUE"""),"Compactos") -> Compactos | E30: =IFERROR(__xludf.DUMMYFUNCTION("""COMPUTED_VALUE"""),"https://docs.fivem.net/vehicles/issi8.webp") -> https://docs.fivem.net/vehicles/issi8.webp
A31: =IFERROR(__xludf.DUMMYFUNCTION("""COMPUTED_VALUE"""),"kanjo") -> kanjo | B31: =IFERROR(__xludf.DUMMYFUNCTION("""COMPUTED_VALUE"""),"Blista Kanjo") -> Blista Kanjo | C31: =IFERROR(__xludf.DUMMYFUNCTION("""COMPUTED_VALUE"""),12000) -> 12000 | D31: =IFERROR(__xludf.DUMMYFUNCTION("""COMPUTED_VALUE"""),"Compactos") -> Compactos | E31: =IFERROR(__xludf.DUMMYFUNCTION("""COMPUTED_VALUE"""),"https://docs.fivem.net/vehicles/kanjo.webp") -> https://docs.fivem.net/vehicles/kanjo.webp
A32: =IFERROR(__xludf.DUMMYFUNCTION("""COMPUTED_VALUE"""),"panto") -> panto | B32: =IFERROR(__xludf.DUMMYFUNCTION("""COMPUTED_VALUE"""),"Panto") -> Panto | C32: =IFERROR(__xludf.DUMMYFUNCTION("""COMPUTED_VALUE"""),9000) -> 9000 | D32: =IFERROR(__xludf.DUMMYFUNCTION("""COMPUTED_VALUE"""),"Compactos") -> Compactos | E32: =IFERROR(__xludf.DUMMYFUNCTION("""COMPUTED_VALUE"""),"https://docs.fivem.net/vehicles/panto.webp") -> https://docs.fivem.net/vehicles/panto.webp
A33: =IFERROR(__xludf.DUMMYFUNCTION("""COMPUTED_VALUE"""),"prairie") -> prairie | B33: =IFERROR(__xludf.DUMMYFUNCTION("""COMPUTED_VALUE"""),"Prairie") -> Prairie | C33: =IFERROR(__xludf.DUMMYFUNCTION("""COMPUTED_VALUE"""),8500) -> 8500 | D33: =IFERROR(__xludf.DUMMYFUNCTION("""COMPUTED_VALUE"""),"Compactos") -> Compactos | E33: =IFERROR(__xludf.DUMMYFUNCTION("""COMPUTED_VALUE"""),"https://docs.fivem.net/vehicles/prairie.webp") -> https://docs.fivem.net/vehicles/prairie.webp
A34: =IFERROR(__xludf.DUMMYFUNCTION("""COMPUTED_VALUE"""),"rhapsody") -> rhapsody | B34: =IFERROR(__xludf.DUMMYFUNCTION("""COMPUTED_VALUE"""),"Rhapsody") -> Rhapsody | C34: =IFERROR(__xludf.DUMMYFUNCTION("""COMPUTED_VALUE"""),12500) -> 12500 | D34: =IFERROR(__xludf.DUMMYFUNCTION("""COMPUTED_VALUE"""),"Compactos") -> Compactos | E34: =IFERROR(__xludf.DUMMYFUNCTION("""COMPUTED_VALUE"""),"https://docs.fivem.net/vehicles/rhapsody.webp") -> https://docs.fivem.net/vehicles/rhapsody.webp
A35: =IFERROR(__xludf.DUMMYFUNCTION("""COMPUTED_VALUE"""),"weevil") -> weevil | B35: =IFERROR(__xludf.DUMMYFUNCTION("""COMPUTED_VALUE"""),"Weevil") -> Weevil | C35: =IFERROR(__xludf.DUMMYFUNCTION("""COMPUTED_VALUE"""),4500) -> 4500 | D35: =IFERROR(__xludf.DUMMYFUNCTION("""COMPUTED_VALUE"""),"Compactos") -> Compactos | E35: =IFERROR(__xludf.DUMMYFUNCTION("""COMPUTED_VALUE"""),"https://docs.fivem.net/vehicles/weevil.webp") -> https://docs.fivem.net/vehicles/weevil.webp
A36: =IFERROR(__xludf.DUMMYFUNCTION("""COMPUTED_VALUE"""),"broadway") -> broadway | B36: =IFERROR(__xludf.DUMMYFUNCTION("""COMPUTED_VALUE"""),"Broadway") -> Broadway | C36: =IFERROR(__xludf.DUMMYFUNCTION("""COMPUTED_VALUE"""),29000) -> 29000 | D36: =IFERROR(__xludf.DUMMYFUNCTION("""COMPUTED_VALUE"""),"Coupes") -> Coupes | E36: =IFERROR(__xludf.DUMMYFUNCTION("""COMPUTED_VALUE"""),"https://docs.fivem.net/vehicles/broadway.webp") -> https://docs.fivem.net/vehicles/broadway.webp
A37: =IFERROR(__xludf.DUMMYFUNCTION("""COMPUTED_VALUE"""),"champion") -> champion | B37: =IFERROR(__xludf.DUMMYFUNCTION("""COMPUTED_VALUE"""),"Champion") -> Champion | C37: =IFERROR(__xludf.DUMMYFUNCTION("""COMPUTED_VALUE"""),125000) -> 125000 | D37: =IFERROR(__xludf.DUMMYFUNCTION("""COMPUTED_VALUE"""),"Coupes") -> Coupes | E37: =IFERROR(__xludf.DUMMYFUNCTION("""COMPUTED_VALUE"""),"https://docs.fivem.net/vehicles/champion.webp") -> https://docs.fivem.net/vehicles/champion.webp
A38: =IFERROR(__xludf.DUMMYFUNCTION("""COMPUTED_VALUE"""),"cogcabrio") -> cogcabrio | B38: =IFERROR(__xludf.DUMMYFUNCTION("""COMPUTED_VALUE"""),"Cognoscenti Cabrio") -> Cognoscenti Cabrio | C38: =IFERROR(__xludf.DUMMYFUNCTION("""COMPUTED_VALUE"""),14000) -> 14000 | D38: =IFERROR(__xludf.DUMMYFUNCTION("""COMPUTED_VALUE"""),"Coupes") -> Coupes | E38: =IFERROR(__xludf.DUMMYFUNCTION("""COMPUTED_VALUE"""),"https://docs.fivem.net/vehicles/cogcabrio.webp") -> https://docs.fivem.net/vehicles/cogcabrio.webp
A39: =IFERROR(__xludf.DUMMYFUNCTION("""COMPUTED_VALUE"""),"cognoscenti") -> cognoscenti | B39: =IFERROR(__xludf.DUMMYFUNCTION("""COMPUTED_VALUE"""),"Cognoscenti") -> Cognoscenti | C39: =IFERROR(__xludf.DUMMYFUNCTION("""COMPUTED_VALUE"""),12000) -> 12000 | D39: =IFERROR(__xludf.DUMMYFUNCTION("""COMPUTED_VALUE"""),"Coupes") -> Coupes | E39: =IFERROR(__xludf.DUMMYFUNCTION("""COMPUTED_VALUE"""),"https://docs.fivem.net/vehicles/cognoscenti.webp") -> https://docs.fivem.net/vehicles/cognoscenti.webp
A40: =IFERROR(__xludf.DUMMYFUNCTION("""COMPUTED_VALUE"""),"exemplar") -> exemplar | B40: =IFERROR(__xludf.DUMMYFUNCTION("""COMPUTED_VALUE"""),"Exemplar") -> Exemplar | C40: =IFERROR(__xludf.DUMMYFUNCTION("""COMPUTED_VALUE"""),40000) -> 40000 | D40: =IFERROR(__xludf.DUMMYFUNCTION("""COMPUTED_VALUE"""),"Coupes") -> Coupes | E40: =IFERROR(__xludf.DUMMYFUNCTION("""COMPUTED_VALUE"""),"https://docs.fivem.net/vehicles/exemplar.webp") -> https://docs.fivem.net/vehicles/exemplar.webp
A41: =IFERROR(__xludf.DUMMYFUNCTION("""COMPUTED_VALUE"""),"f620") -> f620 | B41: =IFERROR(__xludf.DUMMYFUNCTION("""COMPUTED_VALUE"""),"F620") -> F620 | C41: =IFERROR(__xludf.DUMMYFUNCTION("""COMPUTED_VALUE"""),52000) -> 52000 | D41: =IFERROR(__xludf.DUMMYFUNCTION("""COMPUTED_VALUE"""),"Coupes") -> Coupes | E41: =IFERROR(__xludf.DUMMYFUNCTION("""COMPUTED_VALUE"""),"https://docs.fivem.net/vehicles/f620.webp") -> https://docs.fivem.net/vehicles/f620.webp
A42: =IFERROR(__xludf.DUMMYFUNCTION("""COMPUTED_VALUE"""),"felon") -> felon | B42: =IFERROR(__xludf.DUMMYFUNCTION("""COMPUTED_VALUE"""),"Felon") -> Felon | C42: =IFERROR(__xludf.DUMMYFUNCTION("""COMPUTED_VALUE"""),52000) -> 52000 | D42: =IFERROR(__xludf.DUMMYFUNCTION("""COMPUTED_VALUE"""),"Coupes") -> Coupes | E42: =IFERROR(__xludf.DUMMYFUNCTION("""COMPUTED_VALUE"""),"https://docs.fivem.net/vehicles/felon.webp") -> https://docs.fivem.net/vehicles/felon.webp
A43: =IFERROR(__xludf.DUMMYFUNCTION("""COMPUTED_VALUE"""),"felon2") -> felon2 | B43: =IFERROR(__xludf.DUMMYFUNCTION("""COMPUTED_VALUE"""),"Felon GT") -> Felon GT | C43: =IFERROR(__xludf.DUMMYFUNCTION("""COMPUTED_VALUE"""),54000) -> 54000 | D43: =IFERROR(__xludf.DUMMYFUNCTION("""COMPUTED_VALUE"""),"Coupes") -> Coupes | E43: =IFERROR(__xludf.DUMMYFUNCTION("""COMPUTED_VALUE"""),"https://docs.fivem.net/vehicles/felon2.webp") -> https://docs.fivem.net/vehicles/felon2.webp
A44: =IFERROR(__xludf.DUMMYFUNCTION("""COMPUTED_VALUE"""),"fr36") -> fr36 | B44: =IFERROR(__xludf.DUMMYFUNCTION("""COMPUTED_VALUE"""),"FR36") -> FR36 | C44: =IFERROR(__xludf.DUMMYFUNCTION("""COMPUTED_VALUE"""),63000) -> 63000 | D44: =IFERROR(__xludf.DUMMYFUNCTION("""COMPUTED_VALUE"""),"Coupes") -> Coupes | E44: =IFERROR(__xludf.DUMMYFUNCTION("""COMPUTED_VALUE"""),"https://docs.fivem.net/vehicles/fr36.webp") -> https://docs.fivem.net/vehicles/fr36.webp
A45: =IFERROR(__xludf.DUMMYFUNCTION("""COMPUTED_VALUE"""),"futo") -> futo | B45: =IFERROR(__xludf.DUMMYFUNCTION("""COMPUTED_VALUE"""),"Futo") -> Futo | C45: =IFERROR(__xludf.DUMMYFUNCTION("""COMPUTED_VALUE"""),25000) -> 25000 | D45: =IFERROR(__xludf.DUMMYFUNCTION("""COMPUTED_VALUE"""),"Coupes") -> Coupes | E45: =IFERROR(__xludf.DUMMYFUNCTION("""COMPUTED_VALUE"""),"https://docs.fivem.net/vehicles/futo.webp") -> https://docs.fivem.net/vehicles/futo.webp
A46: =IFERROR(__xludf.DUMMYFUNCTION("""COMPUTED_VALUE"""),"jackal") -> jackal | B46: =IFERROR(__xludf.DUMMYFUNCTION("""COMPUTED_VALUE"""),"Jackal") -> Jackal | C46: =IFERROR(__xludf.DUMMYFUNCTION("""COMPUTED_VALUE"""),51500) -> 51500 | D46: =IFERROR(__xludf.DUMMYFUNCTION("""COMPUTED_VALUE"""),"Coupes") -> Coupes | E46: =IFERROR(__xludf.DUMMYFUNCTION("""COMPUTED_VALUE"""),"https://docs.fivem.net/vehicles/jackal.webp") -> https://docs.fivem.net/vehicles/jackal.webp
A47: =IFERROR(__xludf.DUMMYFUNCTION("""COMPUTED_VALUE"""),"kanjosj") -> kanjosj | B47: =IFERROR(__xludf.DUMMYFUNCTION("""COMPUTED_VALUE"""),"Kanjo SJ") -> Kanjo SJ | C47: =IFERROR(__xludf.DUMMYFUNCTION("""COMPUTED_VALUE"""),14500) -> 14500 | D47: =IFERROR(__xludf.DUMMYFUNCTION("""COMPUTED_VALUE"""),"Coupes") -> Coupes | E47: =IFERROR(__xludf.DUMMYFUNCTION("""COMPUTED_VALUE"""),"https://docs.fivem.net/vehicles/kanjosj.webp") -> https://docs.fivem.net/vehicles/kanjosj.webp
A48: =IFERROR(__xludf.DUMMYFUNCTION("""COMPUTED_VALUE"""),"oracle2") -> oracle2 | B48: =IFERROR(__xludf.DUMMYFUNCTION("""COMPUTED_VALUE"""),"Oracle XS") -> Oracle XS | C48: =IFERROR(__xludf.DUMMYFUNCTION("""COMPUTED_VALUE"""),39500) -> 39500 | D48: =IFERROR(__xludf.DUMMYFUNCTION("""COMPUTED_VALUE"""),"Coupes") -> Coupes | E48: =IFERROR(__xludf.DUMMYFUNCTION("""COMPUTED_VALUE"""),"https://docs.fivem.net/vehicles/oracle2.webp") -> https://docs.fivem.net/vehicles/oracle2.webp
A49: =IFERROR(__xludf.DUMMYFUNCTION("""COMPUTED_VALUE"""),"postlude") -> postlude | B49: =IFERROR(__xludf.DUMMYFUNCTION("""COMPUTED_VALUE"""),"Postlude") -> Postlude | C49: =IFERROR(__xludf.DUMMYFUNCTION("""COMPUTED_VALUE"""),27500) -> 27500 | D49: =IFERROR(__xludf.DUMMYFUNCTION("""COMPUTED_VALUE"""),"Coupes") -> Coupes | E49: =IFERROR(__xludf.DUMMYFUNCTION("""COMPUTED_VALUE"""),"https://docs.fivem.net/vehicles/postlude.webp") -> https://docs.fivem.net/vehicles/postlude.webp
A50: =IFERROR(__xludf.DUMMYFUNCTION("""COMPUTED_VALUE"""),"previon") -> previon | B50: =IFERROR(__xludf.DUMMYFUNCTION("""COMPUTED_VALUE"""),"Previon") -> Previon | C50: =IFERROR(__xludf.DUMMYFUNCTION("""COMPUTED_VALUE"""),15000) -> 15000 | D50: =IFERROR(__xludf.DUMMYFUNCTION("""COMPUTED_VALUE"""),"Coupes") -> Coupes | E50: =IFERROR(__xludf.DUMMYFUNCTION("""COMPUTED_VALUE"""),"https://docs.fivem.net/vehicles/previon.webp") -> https://docs.fivem.net/vehicles/previon.webp
A51: =IFERROR(__xludf.DUMMYFUNCTION("""COMPUTED_VALUE"""),"sentinel") -> sentinel | B51: =IFERROR(__xludf.DUMMYFUNCTION("""COMPUTED_VALUE"""),"Sentinel") -> Sentinel | C51: =IFERROR(__xludf.DUMMYFUNCTION("""COMPUTED_VALUE"""),35000) -> 35000 | D51: =IFERROR(__xludf.DUMMYFUNCTION("""COMPUTED_VALUE"""),"Coupes") -> Coupes | E51: =IFERROR(__xludf.DUMMYFUNCTION("""COMPUTED_VALUE"""),"https://docs.fivem.net/vehicles/sentinel.webp") -> https://docs.fivem.net/vehicles/sentinel.webp
A52: =IFERROR(__xludf.DUMMYFUNCTION("""COMPUTED_VALUE"""),"sentinel2") -> sentinel2 | B52: =IFERROR(__xludf.DUMMYFUNCTION("""COMPUTED_VALUE"""),"Sentinel XS") -> Sentinel XS | C52: =IFERROR(__xludf.DUMMYFUNCTION("""COMPUTED_VALUE"""),37000) -> 37000 | D52: =IFERROR(__xludf.DUMMYFUNCTION("""COMPUTED_VALUE"""),"Coupes") -> Coupes | E52: =IFERROR(__xludf.DUMMYFUNCTION("""COMPUTED_VALUE"""),"https://docs.fivem.net/vehicles/sentinel2.webp") -> https://docs.fivem.net/vehicles/sentinel2.webp
A53: =IFERROR(__xludf.DUMMYFUNCTION("""COMPUTED_VALUE"""),"sentinel3") -> sentinel3 | B53: =IFERROR(__xludf.DUMMYFUNCTION("""COMPUTED_VALUE"""),"Sentinel Classic") -> Sentinel Classic | C53: =IFERROR(__xludf.DUMMYFUNCTION("""COMPUTED_VALUE"""),70000) -> 70000 | D53: =IFERROR(__xludf.DUMMYFUNCTION("""COMPUTED_VALUE"""),"Coupes") -> Coupes | E53: =IFERROR(__xludf.DUMMYFUNCTION("""COMPUTED_VALUE"""),"https://docs.fivem.net/vehicles/sentinel3.webp") -> https://docs.fivem.net/vehicles/sentinel3.webp
A54: =IFERROR(__xludf.DUMMYFUNCTION("""COMPUTED_VALUE"""),"tahoma") -> tahoma | B54: =IFERROR(__xludf.DUMMYFUNCTION("""COMPUTED_VALUE"""),"Tahoma Coupe") -> Tahoma Coupe | C54: =IFERROR(__xludf.DUMMYFUNCTION("""COMPUTED_VALUE"""),24000) -> 24000 | D54: =IFERROR(__xludf.DUMMYFUNCTION("""COMPUTED_VALUE"""),"Coupes") -> Coupes | E54: =IFERROR(__xludf.DUMMYFUNCTION("""COMPUTED_VALUE"""),"https://docs.fivem.net/vehicles/tahoma.webp") -> https://docs.fivem.net/vehicles/tahoma.webp
A55: =IFERROR(__xludf.DUMMYFUNCTION("""COMPUTED_VALUE"""),"windsor") -> windsor | B55: =IFERROR(__xludf.DUMMYFUNCTION("""COMPUTED_VALUE"""),"Windsor") -> Windsor | C55: =IFERROR(__xludf.DUMMYFUNCTION("""COMPUTED_VALUE"""),69000) -> 69000 | D55: =IFERROR(__xludf.DUMMYFUNCTION("""COMPUTED_VALUE"""),"Coupes") -> Coupes | E55: =IFERROR(__xludf.DUMMYFUNCTION("""COMPUTED_VALUE"""),"https://docs.fivem.net/vehicles/windsor.webp") -> https://docs.fivem.net/vehicles/windsor.webp
A56: =IFERROR(__xludf.DUMMYFUNCTION("""COMPUTED_VALUE"""),"windsor2") -> windsor2 | B56: =IFERROR(__xludf.DUMMYFUNCTION("""COMPUTED_VALUE"""),"Windsor Drop") -> Windsor Drop | C56: =IFERROR(__xludf.DUMMYFUNCTION("""COMPUTED_VALUE"""),73000) -> 73000 | D56: =IFERROR(__xludf.DUMMYFUNCTION("""COMPUTED_VALUE"""),"Coupes") -> Coupes | E56: =IFERROR(__xludf.DUMMYFUNCTION("""COMPUTED_VALUE"""),"https://docs.fivem.net/vehicles/windsor2.webp") -> https://docs.fivem.net/vehicles/windsor2.webp
A57: =IFERROR(__xludf.DUMMYFUNCTION("""COMPUTED_VALUE"""),"zion") -> zion | B57: =IFERROR(__xludf.DUMMYFUNCTION("""COMPUTED_VALUE"""),"Zion") -> Zion | C57: =IFERROR(__xludf.DUMMYFUNCTION("""COMPUTED_VALUE"""),44000) -> 44000 | D57: =IFERROR(__xludf.DUMMYFUNCTION("""COMPUTED_VALUE"""),"Coupes") -> Coupes | E57: =IFERROR(__xludf.DUMMYFUNCTION("""COMPUTED_VALUE"""),"https://docs.fivem.net/vehicles/zion.webp") -> https://docs.fivem.net/vehicles/zion.webp
A58: =IFERROR(__xludf.DUMMYFUNCTION("""COMPUTED_VALUE"""),"zion2") -> zion2 | B58: =IFERROR(__xludf.DUMMYFUNCTION("""COMPUTED_VALUE"""),"Zion Cabrio") -> Zion Cabrio | C58: =IFERROR(__xludf.DUMMYFUNCTION("""COMPUTED_VALUE"""),46000) -> 46000 | D58: =IFERROR(__xludf.DUMMYFUNCTION("""COMPUTED_VALUE"""),"Coupes") -> Coupes | E58: =IFERROR(__xludf.DUMMYFUNCTION("""COMPUTED_VALUE"""),"https://docs.fivem.net/vehicles/zion2.webp") -> https://docs.fivem.net/vehicles/zion2.webp
A59: =IFERROR(__xludf.DUMMYFUNCTION("""COMPUTED_VALUE"""),"alpha") -> alpha | B59: =IFERROR(__xludf.DUMMYFUNCTION("""COMPUTED_VALUE"""),"Alpha") -> Alpha | C59: =IFERROR(__xludf.DUMMYFUNCTION("""COMPUTED_VALUE"""),59000) -> 59000 | D59: =IFERROR(__xludf.DUMMYFUNCTION("""COMPUTED_VALUE"""),"Deportivo") -> Deportivo | E59: =IFERROR(__xludf.DUMMYFUNCTION("""COMPUTED_VALUE"""),"https://docs.fivem.net/vehicles/alpha.webp") -> https://docs.fivem.net/vehicles/alpha.webp
A60: =IFERROR(__xludf.DUMMYFUNCTION("""COMPUTED_VALUE"""),"banshee") -> banshee | B60: =IFERROR(__xludf.DUMMYFUNCTION("""COMPUTED_VALUE"""),"Banshee") -> Banshee | C60: =IFERROR(__xludf.DUMMYFUNCTION("""COMPUTED_VALUE"""),80000) -> 80000 | D60: =IFERROR(__xludf.DUMMYFUNCTION("""COMPUTED_VALUE"""),"Deportivo") -> Deportivo | E60: =IFERROR(__xludf.DUMMYFUNCTION("""COMPUTED_VALUE"""),"https://docs.fivem.net/vehicles/banshee.webp") -> https://docs.fivem.net/vehicles/banshee.webp
A61: =IFERROR(__xludf.DUMMYFUNCTION("""COMPUTED_VALUE"""),"bestiagts") -> bestiagts | B61: =IFERROR(__xludf.DUMMYFUNCTION("""COMPUTED_VALUE"""),"Bestia GTS") -> Bestia GTS | C61: =IFERROR(__xludf.DUMMYFUNCTION("""COMPUTED_VALUE"""),88000) -> 88000 | D61: =IFERROR(__xludf.DUMMYFUNCTION("""COMPUTED_VALUE"""),"Deportivo") -> Deportivo | E61: =IFERROR(__xludf.DUMMYFUNCTION("""COMPUTED_VALUE"""),"https://docs.fivem.net/vehicles/bestiagts.webp") -> https://docs.fivem.net/vehicles/bestiagts.webp
A62: =IFERROR(__xludf.DUMMYFUNCTION("""COMPUTED_VALUE"""),"calico") -> calico | B62: =IFERROR(__xludf.DUMMYFUNCTION("""COMPUTED_VALUE"""),"Calico GTF") -> Calico GTF | C62: =IFERROR(__xludf.DUMMYFUNCTION("""COMPUTED_VALUE"""),115000) -> 115000 | D62: =IFERROR(__xludf.DUMMYFUNCTION("""COMPUTED_VALUE"""),"Deportivo") -> Deportivo | E62: =IFERROR(__xludf.DUMMYFUNCTION("""COMPUTED_VALUE"""),"https://docs.fivem.net/vehicles/calico.webp") -> https://docs.fivem.net/vehicles/calico.webp
A63: =IFERROR(__xludf.DUMMYFUNCTION("""COMPUTED_VALUE"""),"carbonizzare") -> carbonizzare | B63: =IFERROR(__xludf.DUMMYFUNCTION("""COMPUTED_VALUE"""),"Carbonizzare") -> Carbonizzare | C63: =IFERROR(__xludf.DUMMYFUNCTION("""COMPUTED_VALUE"""),109000) -> 109000 | D63: =IFERROR(__xludf.DUMMYFUNCTION("""COMPUTED_VALUE"""),"Deportivo") -> Deportivo | E63: =IFERROR(__xludf.DUMMYFUNCTION("""COMPUTED_VALUE"""),"https://docs.fivem.net/vehicles/carbonizzare.webp") -> https://docs.fivem.net/vehicles/carbonizzare.webp
A64: =IFERROR(__xludf.DUMMYFUNCTION("""COMPUTED_VALUE"""),"cheetah2") -> cheetah2 | B64: =IFERROR(__xludf.DUMMYFUNCTION("""COMPUTED_VALUE"""),"Cheetah Classic") -> Cheetah Classic | C64: =IFERROR(__xludf.DUMMYFUNCTION("""COMPUTED_VALUE"""),195000) -> 195000 | D64: =IFERROR(__xludf.DUMMYFUNCTION("""COMPUTED_VALUE"""),"Deportivo") -> Deportivo | E64: =IFERROR(__xludf.DUMMYFUNCTION("""COMPUTED_VALUE"""),"https://docs.fivem.net/vehicles/cheetah2.webp") -> https://docs.fivem.net/vehicles/cheetah2.webp
A65: =IFERROR(__xludf.DUMMYFUNCTION("""COMPUTED_VALUE"""),"comet2") -> comet2 | B65: =IFERROR(__xludf.DUMMYFUNCTION("""COMPUTED_VALUE"""),"Comet") -> Comet | C65: =IFERROR(__xludf.DUMMYFUNCTION("""COMPUTED_VALUE"""),98500) -> 98500 | D65: =IFERROR(__xludf.DUMMYFUNCTION("""COMPUTED_VALUE"""),"Deportivo") -> Deportivo | E65: =IFERROR(__xludf.DUMMYFUNCTION("""COMPUTED_VALUE"""),"https://docs.fivem.net/vehicles/comet2.webp") -> https://docs.fivem.net/vehicles/comet2.webp
A66: =IFERROR(__xludf.DUMMYFUNCTION("""COMPUTED_VALUE"""),"comet3") -> comet3 | B66: =IFERROR(__xludf.DUMMYFUNCTION("""COMPUTED_VALUE"""),"Comet Retro Custom") -> Comet Retro Custom | C66: =IFERROR(__xludf.DUMMYFUNCTION("""COMPUTED_VALUE"""),115000) -> 115000 | D66: =IFERROR(__xludf.DUMMYFUNCTION("""COMPUTED_VALUE"""),"Deportivo") -> Deportivo | E66: =IFERROR(__xludf.DUMMYFUNCTION("""COMPUTED_VALUE"""),"https://docs.fivem.net/vehicles/comet3.webp") -> https://docs.fivem.net/vehicles/comet3.webp
A67: =IFERROR(__xludf.DUMMYFUNCTION("""COMPUTED_VALUE"""),"comet4") -> comet4 | B67: =IFERROR(__xludf.DUMMYFUNCTION("""COMPUTED_VALUE"""),"Comet Safari") -> Comet Safari | C67: =IFERROR(__xludf.DUMMYFUNCTION("""COMPUTED_VALUE"""),69500) -> 69500 | D67: =IFERROR(__xludf.DUMMYFUNCTION("""COMPUTED_VALUE"""),"Deportivo") -> Deportivo | E67: =IFERROR(__xludf.DUMMYFUNCTION("""COMPUTED_VALUE"""),"https://docs.fivem.net/vehicles/comet4.webp") -> https://docs.fivem.net/vehicles/comet4.webp
A68: =IFERROR(__xludf.DUMMYFUNCTION("""COMPUTED_VALUE"""),"comet5") -> comet5 | B68: =IFERROR(__xludf.DUMMYFUNCTION("""COMPUTED_VALUE"""),"Comet SR") -> Comet SR | C68: =IFERROR(__xludf.DUMMYFUNCTION("""COMPUTED_VALUE"""),125000) -> 125000 | D68: =IFERROR(__xludf.DUMMYFUNCTION("""COMPUTED_VALUE"""),"Deportivo") -> Deportivo | E68: =IFERROR(__xludf.DUMMYFUNCTION("""COMPUTED_VALUE"""),"https://docs.fivem.net/vehicles/comet5.webp") -> https://docs.fivem.net/vehicles/comet5.webp
A69: =IFERROR(__xludf.DUMMYFUNCTION("""COMPUTED_VALUE"""),"comet6") -> comet6 | B69: =IFERROR(__xludf.DUMMYFUNCTION("""COMPUTED_VALUE"""),"Comet S2") -> Comet S2 | C69: =IFERROR(__xludf.DUMMYFUNCTION("""COMPUTED_VALUE"""),165000) -> 165000 | D69: =IFERROR(__xludf.DUMMYFUNCTION("""COMPUTED_VALUE"""),"Deportivo") -> Deportivo | E69: =IFERROR(__xludf.DUMMYFUNCTION("""COMPUTED_VALUE"""),"https://docs.fivem.net/vehicles/comet6.webp") -> https://docs.fivem.net/vehicles/comet6.webp
A70: =IFERROR(__xludf.DUMMYFUNCTION("""COMPUTED_VALUE"""),"comet7") -> comet7 | B70: =IFERROR(__xludf.DUMMYFUNCTION("""COMPUTED_VALUE"""),"Comet") -> Comet | C70: =IFERROR(__xludf.DUMMYFUNCTION("""COMPUTED_VALUE"""),178000) -> 178000 | D70: =IFERROR(__xludf.DUMMYFUNCTION("""COMPUTED_VALUE"""),"Deportivo") -> Deportivo | E70: =IFERROR(__xludf.DUMMYFUNCTION("""COMPUTED_VALUE"""),"https://docs.fivem.net/vehicles/comet7.webp") -> https://docs.fivem.net/vehicles/comet7.webp
A71: =IFERROR(__xludf.DUMMYFUNCTION("""COMPUTED_VALUE"""),"coquette") -> coquette | B71: =IFERROR(__xludf.DUMMYFUNCTION("""COMPUTED_VALUE"""),"Coquette") -> Coquette | C71: =IFERROR(__xludf.DUMMYFUNCTION("""COMPUTED_VALUE"""),85000) -> 85000 | D71: =IFERROR(__xludf.DUMMYFUNCTION("""COMPUTED_VALUE"""),"Deportivo") -> Deportivo | E71: =IFERROR(__xludf.DUMMYFUNCTION("""COMPUTED_VALUE"""),"https://docs.fivem.net/vehicles/coquette.webp") -> https://docs.fivem.net/vehicles/coquette.webp
A72: =IFERROR(__xludf.DUMMYFUNCTION("""COMPUTED_VALUE"""),"coquette4") -> coquette4 | B72: =IFERROR(__xludf.DUMMYFUNCTION("""COMPUTED_VALUE"""),"Coquette D10") -> Coquette D10 | C72: =IFERROR(__xludf.DUMMYFUNCTION("""COMPUTED_VALUE"""),190000) -> 190000 | D72: =IFERROR(__xludf.DUMMYFUNCTION("""COMPUTED_VALUE"""),"Deportivo") -> Deportivo | E72: =IFERROR(__xludf.DUMMYFUNCTION("""COMPUTED_VALUE"""),"https://docs.fivem.net/vehicles/coquette4.webp") -> https://docs.fivem.net/vehicles/coquette4.webp
A73: =IFERROR(__xludf.DUMMYFUNCTION("""COMPUTED_VALUE"""),"coquette5") -> coquette5 | B73: =IFERROR(__xludf.DUMMYFUNCTION("""COMPUTED_VALUE"""),"Coquette D1") -> Coquette D1 | C73: =IFERROR(__xludf.DUMMYFUNCTION("""COMPUTED_VALUE"""),165000) -> 165000 | D73: =IFERROR(__xludf.DUMMYFUNCTION("""COMPUTED_VALUE"""),"Deportivo") -> Deportivo | E73: =IFERROR(__xludf.DUMMYFUNCTION("""COMPUTED_VALUE"""),"https://docs.fivem.net/vehicles/coquette5.webp") -> https://docs.fivem.net/vehicles/coquette5.webp
A74: =IFERROR(__xludf.DUMMYFUNCTION("""COMPUTED_VALUE"""),"corsita") -> corsita | B74: =IFERROR(__xludf.DUMMYFUNCTION("""COMPUTED_VALUE"""),"Corsita") -> Corsita | C74: =IFERROR(__xludf.DUMMYFUNCTION("""COMPUTED_VALUE"""),188000) -> 188000 | D74: =IFERROR(__xludf.DUMMYFUNCTION("""COMPUTED_VALUE"""),"Deportivo") -> Deportivo | E74: =IFERROR(__xludf.DUMMYFUNCTION("""COMPUTED_VALUE"""),"https://docs.fivem.net/vehicles/corsita.webp") -> https://docs.fivem.net/vehicles/corsita.webp
A75: =IFERROR(__xludf.DUMMYFUNCTION("""COMPUTED_VALUE"""),"coureur") -> coureur | B75: =IFERROR(__xludf.DUMMYFUNCTION("""COMPUTED_VALUE"""),"La Coureuse") -> La Coureuse | C75: =IFERROR(__xludf.DUMMYFUNCTION("""COMPUTED_VALUE"""),85000) -> 85000 | D75: =IFERROR(__xludf.DUMMYFUNCTION("""COMPUTED_VALUE"""),"Deportivo") -> Deportivo | E75: =IFERROR(__xludf.DUMMYFUNCTION("""COMPUTED_VALUE"""),"https://docs.fivem.net/vehicles/coureur.webp") -> https://docs.fivem.net/vehicles/coureur.webp
A76: =IFERROR(__xludf.DUMMYFUNCTION("""COMPUTED_VALUE"""),"cypher") -> cypher | B76: =IFERROR(__xludf.DUMMYFUNCTION("""COMPUTED_VALUE"""),"Cypher") -> Cypher | C76: =IFERROR(__xludf.DUMMYFUNCTION("""COMPUTED_VALUE"""),78000) -> 78000 | D76: =IFERROR(__xludf.DUMMYFUNCTION("""COMPUTED_VALUE"""),"Deportivo") -> Deportivo | E76: =IFERROR(__xludf.DUMMYFUNCTION("""COMPUTED_VALUE"""),"https://docs.fivem.net/vehicles/cypher.webp") -> https://docs.fivem.net/vehicles/cypher.webp
A77: =IFERROR(__xludf.DUMMYFUNCTION("""COMPUTED_VALUE"""),"drafter") -> drafter | B77: =IFERROR(__xludf.DUMMYFUNCTION("""COMPUTED_VALUE"""),"8F Drafter") -> 8F Drafter | C77: =IFERROR(__xludf.DUMMYFUNCTION("""COMPUTED_VALUE"""),85000) -> 85000 | D77: =IFERROR(__xludf.DUMMYFUNCTION("""COMPUTED_VALUE"""),"Deportivo") -> Deportivo | E77: =IFERROR(__xludf.DUMMYFUNCTION("""COMPUTED_VALUE"""),"https://docs.fivem.net/vehicles/drafter.webp") -> https://docs.fivem.net/vehicles/drafter.webp
A78: =IFERROR(__xludf.DUMMYFUNCTION("""COMPUTED_VALUE"""),"driftcypher") -> driftcypher | B78: =IFERROR(__xludf.DUMMYFUNCTION("""COMPUTED_VALUE"""),"Drift Cypher") -> Drift Cypher | C78: =IFERROR(__xludf.DUMMYFUNCTION("""COMPUTED_VALUE"""),83000) -> 83000 | D78: =IFERROR(__xludf.DUMMYFUNCTION("""COMPUTED_VALUE"""),"Deportivo") -> Deportivo | E78: =IFERROR(__xludf.DUMMYFUNCTION("""COMPUTED_VALUE"""),"https://docs.fivem.net/vehicles/driftcypher.webp") -> https://docs.fivem.net/vehicles/driftcypher.webp
A79: =IFERROR(__xludf.DUMMYFUNCTION("""COMPUTED_VALUE"""),"driftsentinel") -> driftsentinel | B79: =IFERROR(__xludf.DUMMYFUNCTION("""COMPUTED_VALUE"""),"Drift Sentinel Classic") -> Drift Sentinel Classic | C79: =IFERROR(__xludf.DUMMYFUNCTION("""COMPUTED_VALUE"""),75000) -> 75000 | D79: =IFERROR(__xludf.DUMMYFUNCTION("""COMPUTED_VALUE"""),"Deportivo") -> Deportivo | E79: =IFERROR(__xludf.DUMMYFUNCTION("""COMPUTED_VALUE"""),"https://docs.fivem.net/vehicles/driftsentinel.webp") -> https://docs.fivem.net/vehicles/driftsentinel.webp
A80: =IFERROR(__xludf.DUMMYFUNCTION("""COMPUTED_VALUE"""),"driftvorschlag") -> driftvorschlag | B80: =IFERROR(__xludf.DUMMYFUNCTION("""COMPUTED_VALUE"""),"Vorschlaghammer Drift") -> Vorschlaghammer Drift | C80: =IFERROR(__xludf.DUMMYFUNCTION("""COMPUTED_VALUE"""),70000) -> 70000 | D80: =IFERROR(__xludf.DUMMYFUNCTION("""COMPUTED_VALUE"""),"Deportivo") -> Deportivo | E80: =IFERROR(__xludf.DUMMYFUNCTION("""COMPUTED_VALUE"""),"https://docs.fivem.net/vehicles/driftvorschlag.webp") -> https://docs.fivem.net/vehicles/driftvorschlag.webp
A81: =IFERROR(__xludf.DUMMYFUNCTION("""COMPUTED_VALUE"""),"elegy") -> elegy | B81: =IFERROR(__xludf.DUMMYFUNCTION("""COMPUTED_VALUE"""),"Elegy Retro Custom") -> Elegy Retro Custom | C81: =IFERROR(__xludf.DUMMYFUNCTION("""COMPUTED_VALUE"""),74000) -> 74000 | D81: =IFERROR(__xludf.DUMMYFUNCTION("""COMPUTED_VALUE"""),"Deportivo") -> Deportivo | E81: =IFERROR(__xludf.DUMMYFUNCTION("""COMPUTED_VALUE"""),"https://docs.fivem.net/vehicles/elegy.webp") -> https://docs.fivem.net/vehicles/elegy.webp
A82: =IFERROR(__xludf.DUMMYFUNCTION("""COMPUTED_VALUE"""),"elegy2") -> elegy2 | B82: =IFERROR(__xludf.DUMMYFUNCTION("""COMPUTED_VALUE"""),"Elegy RH8") -> Elegy RH8 | C82: =IFERROR(__xludf.DUMMYFUNCTION("""COMPUTED_VALUE"""),78000) -> 78000 | D82: =IFERROR(__xludf.DUMMYFUNCTION("""COMPUTED_VALUE"""),"Deportivo") -> Deportivo | E82: =IFERROR(__xludf.DUMMYFUNCTION("""COMPUTED_VALUE"""),"https://docs.fivem.net/vehicles/elegy2.webp") -> https://docs.fivem.net/vehicles/elegy2.webp
A83: =IFERROR(__xludf.DUMMYFUNCTION("""COMPUTED_VALUE"""),"euros") -> euros | B83: =IFERROR(__xludf.DUMMYFUNCTION("""COMPUTED_VALUE"""),"Euros") -> Euros | C83: =IFERROR(__xludf.DUMMYFUNCTION("""COMPUTED_VALUE"""),80000) -> 80000 | D83: =IFERROR(__xludf.DUMMYFUNCTION("""COMPUTED_VALUE"""),"Deportivo") -> Deportivo | E83: =IFERROR(__xludf.DUMMYFUNCTION("""COMPUTED_VALUE"""),"https://docs.fivem.net/vehicles/euros.webp") -> https://docs.fivem.net/vehicles/euros.webp
A84: =IFERROR(__xludf.DUMMYFUNCTION("""COMPUTED_VALUE"""),"eurosX32") -> eurosX32 | B84: =IFERROR(__xludf.DUMMYFUNCTION("""COMPUTED_VALUE"""),"Euros X32") -> Euros X32 | C84: =IFERROR(__xludf.DUMMYFUNCTION("""COMPUTED_VALUE"""),90000) -> 90000 | D84: =IFERROR(__xludf.DUMMYFUNCTION("""COMPUTED_VALUE"""),"Deportivo") -> Deportivo | E84: =IFERROR(__xludf.DUMMYFUNCTION("""COMPUTED_VALUE"""),"https://docs.fivem.net/vehicles/eurosx32.webp") -> https://docs.fivem.net/vehicles/eurosx32.webp
A85: =IFERROR(__xludf.DUMMYFUNCTION("""COMPUTED_VALUE"""),"everon2") -> everon2 | B85: =IFERROR(__xludf.DUMMYFUNCTION("""COMPUTED_VALUE"""),"Everon Hotring") -> Everon Hotring | C85: =IFERROR(__xludf.DUMMYFUNCTION("""COMPUTED_VALUE"""),85000) -> 85000 | D85: =IFERROR(__xludf.DUMMYFUNCTION("""COMPUTED_VALUE"""),"Deportivo") -> Deportivo | E85: =IFERROR(__xludf.DUMMYFUNCTION("""COMPUTED_VALUE"""),"https://docs.fivem.net/vehicles/everon2.webp") -> https://docs.fivem.net/vehicles/everon2.webp
A86: =IFERROR(__xludf.DUMMYFUNCTION("""COMPUTED_VALUE"""),"feltzer2") -> feltzer2 | B86: =IFERROR(__xludf.DUMMYFUNCTION("""COMPUTED_VALUE"""),"Feltzer") -> Feltzer | C86: =IFERROR(__xludf.DUMMYFUNCTION("""COMPUTED_VALUE"""),82000) -> 82000 | D86: =IFERROR(__xludf.DUMMYFUNCTION("""COMPUTED_VALUE"""),"Deportivo") -> Deportivo | E86: =IFERROR(__xludf.DUMMYFUNCTION("""COMPUTED_VALUE"""),"https://docs.fivem.net/vehicles/feltzer2.webp") -> https://docs.fivem.net/vehicles/feltzer2.webp
A87: =IFERROR(__xludf.DUMMYFUNCTION("""COMPUTED_VALUE"""),"flashgt") -> flashgt | B87: =IFERROR(__xludf.DUMMYFUNCTION("""COMPUTED_VALUE"""),"Flash GT") -> Flash GT | C87: =IFERROR(__xludf.DUMMYFUNCTION("""COMPUTED_VALUE"""),105000) -> 105000 | D87: =IFERROR(__xludf.DUMMYFUNCTION("""COMPUTED_VALUE"""),"Deportivo") -> Deportivo | E87: =IFERROR(__xludf.DUMMYFUNCTION("""COMPUTED_VALUE"""),"https://docs.fivem.net/vehicles/flashgt.webp") -> https://docs.fivem.net/vehicles/flashgt.webp
A88: =IFERROR(__xludf.DUMMYFUNCTION("""COMPUTED_VALUE"""),"furoregt") -> furoregt | B88: =IFERROR(__xludf.DUMMYFUNCTION("""COMPUTED_VALUE"""),"Furore GT") -> Furore GT | C88: =IFERROR(__xludf.DUMMYFUNCTION("""COMPUTED_VALUE"""),87500) -> 87500 | D88: =IFERROR(__xludf.DUMMYFUNCTION("""COMPUTED_VALUE"""),"Deportivo") -> Deportivo | E88: =IFERROR(__xludf.DUMMYFUNCTION("""COMPUTED_VALUE"""),"https://docs.fivem.net/vehicles/furoregt.webp") -> https://docs.fivem.net/vehicles/furoregt.webp
A89: =IFERROR(__xludf.DUMMYFUNCTION("""COMPUTED_VALUE"""),"futo2") -> futo2 | B89: =IFERROR(__xludf.DUMMYFUNCTION("""COMPUTED_VALUE"""),"Futo GTX") -> Futo GTX | C89: =IFERROR(__xludf.DUMMYFUNCTION("""COMPUTED_VALUE"""),39000) -> 39000 | D89: =IFERROR(__xludf.DUMMYFUNCTION("""COMPUTED_VALUE"""),"Deportivo") -> Deportivo | E89: =IFERROR(__xludf.DUMMYFUNCTION("""COMPUTED_VALUE"""),"https://docs.fivem.net/vehicles/futo2.webp") -> https://docs.fivem.net/vehicles/futo2.webp
A90: =IFERROR(__xludf.DUMMYFUNCTION("""COMPUTED_VALUE"""),"gauntlet6") -> gauntlet6 | B90: =IFERROR(__xludf.DUMMYFUNCTION("""COMPUTED_VALUE"""),"Hotring Hellfire") -> Hotring Hellfire | C90: =IFERROR(__xludf.DUMMYFUNCTION("""COMPUTED_VALUE"""),90000) -> 90000 | D90: =IFERROR(__xludf.DUMMYFUNCTION("""COMPUTED_VALUE"""),"Deportivo") -> Deportivo | E90: =IFERROR(__xludf.DUMMYFUNCTION("""COMPUTED_VALUE"""),"https://docs.fivem.net/vehicles/gauntlet6.webp") -> https://docs.fivem.net/vehicles/gauntlet6.webp
A91: =IFERROR(__xludf.DUMMYFUNCTION("""COMPUTED_VALUE"""),"gb200") -> gb200 | B91: =IFERROR(__xludf.DUMMYFUNCTION("""COMPUTED_VALUE"""),"GB 200") -> GB 200 | C91: =IFERROR(__xludf.DUMMYFUNCTION("""COMPUTED_VALUE"""),74000) -> 74000 | D91: =IFERROR(__xludf.DUMMYFUNCTION("""COMPUTED_VALUE"""),"Deportivo") -> Deportivo | E91: =IFERROR(__xludf.DUMMYFUNCTION("""COMPUTED_VALUE"""),"https://docs.fivem.net/vehicles/gb200.webp") -> https://docs.fivem.net/vehicles/gb200.webp
A92: =IFERROR(__xludf.DUMMYFUNCTION("""COMPUTED_VALUE"""),"growler") -> growler | B92: =IFERROR(__xludf.DUMMYFUNCTION("""COMPUTED_VALUE"""),"Growler") -> Growler | C92: =IFERROR(__xludf.DUMMYFUNCTION("""COMPUTED_VALUE"""),115000) -> 115000 | D92: =IFERROR(__xludf.DUMMYFUNCTION("""COMPUTED_VALUE"""),"Deportivo") -> Deportivo | E92: =IFERROR(__xludf.DUMMYFUNCTION("""COMPUTED_VALUE"""),"https://docs.fivem.net/vehicles/growler.webp") -> https://docs.fivem.net/vehicles/growler.webp
A93: =IFERROR(__xludf.DUMMYFUNCTION("""COMPUTED_VALUE"""),"imorgon") -> imorgon | B93: =IFERROR(__xludf.DUMMYFUNCTION("""COMPUTED_VALUE"""),"Imorgon") -> Imorgon | C93: =IFERROR(__xludf.DUMMYFUNCTION("""COMPUTED_VALUE"""),89000) -> 89000 | D93: =IFERROR(__xludf.DUMMYFUNCTION("""COMPUTED_VALUE"""),"Deportivo") -> Deportivo | E93: =IFERROR(__xludf.DUMMYFUNCTION("""COMPUTED_VALUE"""),"https://docs.fivem.net/vehicles/imorgon.webp") -> https://docs.fivem.net/vehicles/imorgon.webp
A94: =IFERROR(__xludf.DUMMYFUNCTION("""COMPUTED_VALUE"""),"italigto") -> italigto | B94: =IFERROR(__xludf.DUMMYFUNCTION("""COMPUTED_VALUE"""),"Itali GTO") -> Itali GTO | C94: =IFERROR(__xludf.DUMMYFUNCTION("""COMPUTED_VALUE"""),215000) -> 215000 | D94: =IFERROR(__xludf.DUMMYFUNCTION("""COMPUTED_VALUE"""),"Deportivo") -> Deportivo | E94: =IFERROR(__xludf.DUMMYFUNCTION("""COMPUTED_VALUE"""),"https://docs.fivem.net/vehicles/italigto.webp") -> https://docs.fivem.net/vehicles/italigto.webp
A95: =IFERROR(__xludf.DUMMYFUNCTION("""COMPUTED_VALUE"""),"jester") -> jester | B95: =IFERROR(__xludf.DUMMYFUNCTION("""COMPUTED_VALUE"""),"Jester") -> Jester | C95: =IFERROR(__xludf.DUMMYFUNCTION("""COMPUTED_VALUE"""),145000) -> 145000 | D95: =IFERROR(__xludf.DUMMYFUNCTION("""COMPUTED_VALUE"""),"Deportivo") -> Deportivo | E95: =IFERROR(__xludf.DUMMYFUNCTION("""COMPUTED_VALUE"""),"https://docs.fivem.net/vehicles/jester.webp") -> https://docs.fivem.net/vehicles/jester.webp
A96: =IFERROR(__xludf.DUMMYFUNCTION("""COMPUTED_VALUE"""),"jester2") -> jester2 | B96: =IFERROR(__xludf.DUMMYFUNCTION("""COMPUTED_VALUE"""),"Jester Racecar") -> Jester Racecar | C96: =IFERROR(__xludf.DUMMYFUNCTION("""COMPUTED_VALUE"""),150000) -> 150000 | D96: =IFERROR(__xludf.DUMMYFUNCTION("""COMPUTED_VALUE"""),"Deportivo") -> Deportivo | E96: =IFERROR(__xludf.DUMMYFUNCTION("""COMPUTED_VALUE"""),"https://docs.fivem.net/vehicles/jester2.webp") -> https://docs.fivem.net/vehicles/jester2.webp
A97: =IFERROR(__xludf.DUMMYFUNCTION("""COMPUTED_VALUE"""),"jester3") -> jester3 | B97: =IFERROR(__xludf.DUMMYFUNCTION("""COMPUTED_VALUE"""),"Jester Classic") -> Jester Classic | C97: =IFERROR(__xludf.DUMMYFUNCTION("""COMPUTED_VALUE"""),147000) -> 147000 | D97: =IFERROR(__xludf.DUMMYFUNCTION("""COMPUTED_VALUE"""),"Deportivo") -> Deportivo | E97: =IFERROR(__xludf.DUMMYFUNCTION("""COMPUTED_VALUE"""),"https://docs.fivem.net/vehicles/jester3.webp") -> https://docs.fivem.net/vehicles/jester3.webp
A98: =IFERROR(__xludf.DUMMYFUNCTION("""COMPUTED_VALUE"""),"jester4") -> jester4 | B98: =IFERROR(__xludf.DUMMYFUNCTION("""COMPUTED_VALUE"""),"Jester RR") -> Jester RR | C98: =IFERROR(__xludf.DUMMYFUNCTION("""COMPUTED_VALUE"""),160000) -> 160000 | D98: =IFERROR(__xludf.DUMMYFUNCTION("""COMPUTED_VALUE"""),"Deportivo") -> Deportivo | E98: =IFERROR(__xludf.DUMMYFUNCTION("""COMPUTED_VALUE"""),"https://docs.fivem.net/vehicles/jester4.webp") -> https://docs.fivem.net/vehicles/jester4.webp
A99: =IFERROR(__xludf.DUMMYFUNCTION("""COMPUTED_VALUE"""),"jugular") -> jugular | B99: =IFERROR(__xludf.DUMMYFUNCTION("""COMPUTED_VALUE"""),"Jugular") -> Jugular | C99: =IFERROR(__xludf.DUMMYFUNCTION("""COMPUTED_VALUE"""),175000) -> 175000 | D99: =IFERROR(__xludf.DUMMYFUNCTION("""COMPUTED_VALUE"""),"Deportivo") -> Deportivo | E99: =IFERROR(__xludf.DUMMYFUNCTION("""COMPUTED_VALUE"""),"https://docs.fivem.net/vehicles/jugular.webp") -> https://docs.fivem.net/vehicles/jugular.webp
A100: =IFERROR(__xludf.DUMMYFUNCTION("""COMPUTED_VALUE"""),"khamelion") -> khamelion | B100: =IFERROR(__xludf.DUMMYFUNCTION("""COMPUTED_VALUE"""),"Khamelion") -> Khamelion | C100: =IFERROR(__xludf.DUMMYFUNCTION("""COMPUTED_VALUE"""),68000) -> 68000 | D100: =IFERROR(__xludf.DUMMYFUNCTION("""COMPUTED_VALUE"""),"Deportivo") -> Deportivo | E100: =IFERROR(__xludf.DUMMYFUNCTION("""COMPUTED_VALUE"""),"https://docs.fivem.net/vehicles/khamelion.webp") -> https://docs.fivem.net/vehicles/khamelion.webp
...
